duckling.py
pyduckling-0.0.1.dist-info/LICENSE
pyduckling-0.0.1.dist-info/METADATA
pyduckling-0.0.1.dist-info/WHEEL
pyduckling-0.0.1.dist-info/top_level.txt
pyduckling-0.0.1.dist-info/RECORD
