Metadata-Version: 2.1
Name: pyduckling
Version: 0.0.1
Summary: Python wrapper for facebook Duckling
Home-page: https://github.com/liuzl/pyduckling
Author: Zhanliang Liu
Author-email: liang@zliu.org
License: UNKNOWN
Platform: UNKNOWN
Classifier: Programming Language :: Python :: 3
Classifier: License :: OSI Approved :: Apache Software License
Classifier: Operating System :: OS Independent
Requires-Python: >=3.6
Requires-Dist: requests
